[{"worldID":1,"startYear":1999,"isRange":1,"building":"city_02","subject":"na"},
    {"worldID":2,"startYear":1951,"isRange":1,"building":"city_01","subject":"na"},
    {"worldID":3,"startYear":1946,"isRange":1,"building":"modern_01","subject":"na"},
    {"worldID":4,"startYear":1939,"isRange":1,"building":"modern_01","subject":"war_01"},
    {"worldID":5,"startYear":1900,"isRange":1,"building":"modern_01","subject":"na"},
    {"worldID":6,"startYear":1830,"isRange":1,"building":"factory_01","subject":"na"},
    {"worldID":7,"startYear":1517,"isRange":1,"building":"town_01","subject":"na"},
    {"worldID":8,"startYear":1488,"isRange":1,"building":"port_01","subject":"na"},
    {"worldID":9,"startYear":1301,"isRange":1,"building":"castle_01","subject":"na"},
    {"worldID":10,"startYear":476,"isRange":1,"building":"church_01","subject":"na"},
    {"worldID":11,"startYear":0,"isRange":1,"building":"rome_01","subject":"na"}]